{
  "package": {
    "name": "ktor-features-zipkin",
    "repo": "maven",
    "subject": "mjstrasser",
    "desc": "Ktor feature for handling Zipkin tracing IDs",
    "website_url": "https://blog.michaelstrasser.com",
    "issue_tracker_url": "https://github.com/mjstrasser/ktor-features-zipkin/issues",
    "vcs_url": "https://github.com/mjstrasser/ktor-features-zipkin.git",
    "licenses": [
      "Apache-2.0"
    ],
    "labels": [
      "kotlin",
      "bintray",
      "gradle"
    ],
    "public_download_numbers": false,
    "public_stats": false
  },
  "version": {
    "name": "0.2.10",
    "released": "2020-03-18",
    "gpgSign": false
  },
  "files": [
    {
      "includePattern": "build/repo/com/michaelstrasser/ktor-features-zipkin/0.2.10/(.*)",
      "uploadPattern": "com/michaelstrasser/ktor-features-zipkin/0.2.10/$1"
    }
  ],
  "publish": true
}